{"development_linux_basic_实验2 makefile实验.md":"B9Bqoauf","development_linux_command_cp.md":"DYm2_g3H","development_linux_frp_frp.md":"DApsKntg","development_conda_conda.md":"DeAd45eP","development_linux_linux-ubuntu.md":"C7izCz6B","development_guide_guide.md":"7VN4LAcp","development_linux_basic_linux-basic.md":"DMhraefA","development_linux_basic_basic.md":"3bTvl6HL","development_tool_ssh_login-to-the-remote-server.md":"CJeVcj2F","development_linux_basic_linux-file_system.md":"BU36Lx1H","development_linux_basic_实验1 linux.md":"DikAsFEs","development_linux_linux.md":"Dh-oCP99","development_vue_vue.md":"D2gi_zFl","development_ubuntu-install_ubuntu-install.md":"BHhbGV-R","development_linux_tmux_tmux.md":"B12ZtOpJ","development_tool_git_command.md":"5254vU4e","fun_homeassistant_homeassistant.md":"CN1Bx54k","development_linux_ubuntu_ubuntu.md":"CZbFYLIW","development_tool_git_git.md":"CQ1UiDQc","development_tool_github_github.md":"CRiKNaBk","development_tool_nginx_nginx.md":"JriWbIV6","hardware_raspberrypi_openwrt.md":"UvLlrRp-","development_tool_ssh_ssh.md":"cy-vCkOm","diary_wuhan23_sunset_wuhan23_sunset.md":"Bl3GVoF8","gadgets_clash_clash.md":"BoDwcLZG","gadgets_mac-about_mac-about.md":"D2hjcF0R","gadgets_mac-gadgets_mac-gadgets.md":"DXuvrc69","machine_learning_object_detection_object_detection.md":"mcnu0PEW","hardware_nezha_nezha.md":"Bficv9nX","development_linux_vim_vim.md":"CS81mU06","hardware_raspberrypi_icm20602.md":"DPxPgPRF","index.md":"De6YurVZ","文档编写技巧.md":"qqcs-Rn7","hardware_raspberrypi_raspberrypi.md":"BTSsQk-9","machine_learning_mlp_mlp.md":"DK-p5gVw","machine_learning_diffusion_model_diffusion_model.md":"B8EYQXki"}
